Topsis_pack/__init__.py
Topsis_pack/topsis.py
Topsis_guransh9-0.0.1.dist-info/LICENSE
Topsis_guransh9-0.0.1.dist-info/METADATA
Topsis_guransh9-0.0.1.dist-info/WHEEL
Topsis_guransh9-0.0.1.dist-info/entry_points.txt
Topsis_guransh9-0.0.1.dist-info/top_level.txt
Topsis_guransh9-0.0.1.dist-info/RECORD
