Metadata-Version: 2.1
Name: Topsis-guransh9
Version: 0.0.1
Summary: A python package to implement Topsis approach
Home-page: https://github.com/pypa/Topsis
Author: Jyot Guransh Singh Dua
Author-email: dua.guransh18@gmail.com
License: UNKNOWN
Platform: UNKNOWN
Classifier: Programming Language :: Python :: 3
Classifier: License :: OSI Approved :: MIT License
Classifier: Operating System :: OS Independent
Requires-Python: >=3
Requires-Dist: requests
